{
	"ec": {
		"2018.2": {
			"pi": {
				"nome": "Programacao Imperativa",
				"Matriculados": 19,
				"Aprovados": 4,
				"Reprovados": 2,
				"Trancados": 0,
				"Cancelados": 0,
				"MediaGeral": 1.18,
				"TaxadeAprovacao": 21.05,
				"TaxadeAprovacaoLiquida": 21.05,
				"MargemDeAprovacaoLiquida": 0
			},
			"pf": {
				"nome": "Programacao Funcional",
				"Matriculados": 51,
				"Aprovados": 16,
				"Reprovados": 24,
				"Trancados": 2,
				"Cancelados": 0,
				"MediaGeral": 2.43,
				"TaxadeAprovacao": 31.37,
				"TaxadeAprovacaoLiquida": 32.65,
				"MargemDeAprovacaoLiquida": 1.28
			},
			"arqui_computadores": {
				"nome": "Arquitetura de Computadores",
				"Matriculados": 83,
				"Aprovados": 51,
				"Reprovados": 26,
				"Trancados": 6,
				"Cancelados": 0,
				"MediaGeral": 5.35,
				"TaxadeAprovacao": 61.45,
				"TaxadeAprovacaoLiquida": 66.23,
				"MargemDeAprovacaoLiquida": 4.79
			},
			"banco_dados_um": {
				"nome": "Banco de Dados I",
				"Matriculados": 3,
				"Aprovados": 3,
				"Reprovados": 0,
				"Trancados": 0,
				"Cancelados": 0,
				"MediaGeral": 7.10,
				"TaxadeAprovacao": 100,
				"TaxadeAprovacaoLiquida": 100,
				"MargemDeAprovacaoLiquida": 0.00
			},
			"compiladores": {
				"nome": "Compiladores",
				"Matriculados": 0,
				"Aprovados": 0,
				"Reprovados": 0,
				"Trancados": 0,
				"Cancelados": 0,
				"MediaGeral": 0,
				"TaxadeAprovacao": 0,
				"TaxadeAprovacaoLiquida": 0,
				"MargemDeAprovacaoLiquida": 0
			},
			"eng_software_um": {
				"nome": "Engenharia de Software I",
				"Matriculados": 28,
				"Aprovados": 20,
				"Reprovados": 6,
				"Trancados": 0,
				"Cancelados": 2,
				"MediaGeral": 5.69,
				"TaxadeAprovacao": 76.92,
				"TaxadeAprovacaoLiquida": 76.92,
				"MargemDeAprovacaoLiquida": 0
			},
			"eng_software_dois": {
				"nome": "Engenharia de Software II",
				"Matriculados": 17,
				"Aprovados": 4,
				"Reprovados": 7,
				"Trancados": 3,
				"Cancelados": 3,
				"MediaGeral": 2.55,
				"TaxadeAprovacao": 28.57,
				"TaxadeAprovacaoLiquida": 36.36,
				"MargemDeAprovacaoLiquida": 7.79
			},

			"estagio_supervisionado_compu": {
				"nome": "Estagio Supervisionado em Computacao",
				"Matriculados": 8,
				"Aprovados": 7,
				"Reprovados": 1,
				"Trancados": 0,
				"Cancelados": 0,
				"MediaGeral": 8.44,
				"TaxadeAprovacao": 87.50,
				"TaxadeAprovacaoLiquida": 87.50,
				"MargemDeAprovacaoLiquida": 0
			},
			"ED": {
				"nome": "Estrutura de Dados",
				"Matriculados": 0,
				"Aprovados": 0,
				"Reprovados": 0,
				"Trancados": 0,
				"Cancelados": 0,
				"MediaGeral": 0,
				"TaxadeAprovacao": 0,
				"TaxadeAprovacaoLiquida": 0,
				"MargemDeAprovacaoLiquida": 0
			},
			"fundamentos_sistemas_digitais": {
				"nome": "Fundamentos de Sistemas Digitais",
				"Matriculados": 0,
				"Aprovados": 0,
				"Reprovados": 0,
				"Trancados": 0,
				"Cancelados": 0,
				"MediaGeral": 0,
				"TaxadeAprovacao": 0,
				"TaxadeAprovacaoLiquida": 0,
				"MargemDeAprovacaoLiquida": 0
			},
			"fundamentos_sistemas_embarcados": {
				"nome": "Fundamentos de Sistemas Embarcados",
				"Matriculados": 76,
				"Aprovados": 61,
				"Reprovados": 10,
				"Trancados": 4,
				"Cancelados": 1,
				"MediaGeral": 8.65,
				"TaxadeAprovacao": 81.33,
				"TaxadeAprovacaoLiquida": 85.92,
				"MargemDeAprovacaoLiquida": 4.58
			},
			"grafos": {
				"nome": "Grafos e Algoritmos Computacionais",
				"Matriculados": 42,
				"Aprovados": 23,
				"Reprovados": 11,
				"Trancados": 4,
				"Cancelados": 4,
				"MediaGeral": 4.95,
				"TaxadeAprovacao": 60.53,
				"TaxadeAprovacaoLiquida": 67.65,
				"MargemDeAprovacaoLiquida": 7.12
			},
			"informatica_et_socie": {
				"nome": "Informatica, Etica e Sociedade",
				"Matriculados": 11,
				"Aprovados": 6,
				"Reprovados": 3,
				"Trancados": 2,
				"Cancelados": 0,
				"MediaGeral": 6.30,
				"TaxadeAprovacao": 54.55,
				"TaxadeAprovacaoLiquida": 66.67,
				"MargemDeAprovacaoLiquida": 12.12
			},
			"inteligencia_artificial": {
				"nome": "Inteligencia Artificial",
				"Matriculados": 5,
				"Aprovados": 4,
				"Reprovados": 0,
				"Trancados": 1,
				"Cancelados": 0,
				"MediaGeral": 5.88,
				"TaxadeAprovacao": 80,
				"TaxadeAprovacaoLiquida": 100,
				"MargemDeAprovacaoLiquida": 20
			},
			"interface_hardware_software": {
				"nome": "Interface Hardware Software",
				"Matriculados": 0,
				"Aprovados": 0,
				"Reprovados": 0,
				"Trancados": 0,
				"Cancelados": 0,
				"MediaGeral": 0,
				"TaxadeAprovacao": 0,
				"TaxadeAprovacaoLiquida": 0,
				"MargemDeAprovacaoLiquida": 0
			},
			"laboratorio_redes_computadores": {
				"nome": "Laboratorio de Redes de Computadores",
				"Matriculados": 20,
				"Aprovados": 15,
				"Reprovados": 1,
				"Trancados": 2,
				"Cancelados": 2,
				"MediaGeral": 7,
				"TaxadeAprovacao": 83.33,
				"TaxadeAprovacaoLiquida": 93.75,
				"MargemDeAprovacaoLiquida": 10.42
			},
			"LFC": {
				"nome": "Linguagens Formais e Computabilidade",
				"Matriculados": 84,
				"Aprovados": 48,
				"Reprovados": 28,
				"Trancados": 3,
				"Cancelados": 5,
				"MediaGeral": 4.73,
				"TaxadeAprovacao": 60.76,
				"TaxadeAprovacaoLiquida": 63.16,
				"MargemDeAprovacaoLiquida": 2.40
			},
			"logica_computacao": {
				"nome": "Logica de Computacao",
				"Matriculados": 1,
				"Aprovados": 0,
				"Reprovados": 1,
				"Trancados": 0,
				"Cancelados": 0,
				"MediaGeral": 0,
				"TaxadeAprovacao": 0,
				"TaxadeAprovacaoLiquida": 0,
				"MargemDeAprovacaoLiquida": 0
			},
			"metodos_tecnicas_pesquisa_compu": {
				"nome": "Metodos e Tecnicas de Pesquisa para Computacao",
				"Matriculados": 19,
				"Aprovados": 2,
				"Reprovados": 13,
				"Trancados": 4,
				"Cancelados": 0,
				"MediaGeral": 1.02,
				"TaxadeAprovacao": 10.53,
				"TaxadeAprovacaoLiquida": 13.33,
				"MargemDeAprovacaoLiquida": 2.81
			},
			"pratica_sistemas_digi": {
				"nome": "Praticas em Sistemas Digitais",
				"Matriculados": 0,
				"Aprovados": 0,
				"Reprovados": 0,
				"Trancados": 0,
				"Cancelados": 0,
				"MediaGeral": 0,
				"TaxadeAprovacao": 70,
				"TaxadeAprovacaoLiquida": 0,
				"MargemDeAprovacaoLiquida": 0
			},
			"pratica_orientada_em_comp_um": {
				"nome": "Pratica Orientada em Computacao I",
				"Matriculados": 24,
				"Aprovados": 8,
				"Reprovados": 2,
				"Trancados": 1,
				"Cancelados": 13,
				"MediaGeral": 5.81,
				"TaxadeAprovacao": 72.73,
				"TaxadeAprovacaoLiquida": 80,
				"MargemDeAprovacaoLiquida": 7.27
			},
			"pratica_orientada_em_comp_dois": {
				"nome": "Pratica Orientada em Computacao II",
				"Matriculados": 0,
				"Aprovados": 0,
				"Reprovados": 0,
				"Trancados": 0,
				"Cancelados": 0,
				"MediaGeral": 0,
				"TaxadeAprovacao": 0,
				"TaxadeAprovacaoLiquida": 0,
				"MargemDeAprovacaoLiquida": 0
			},
			"POO": {
				"nome": "Programacao Orientada a Objetos",
				"Matriculados": 43,
				"Aprovados": 20,
				"Reprovados": 21,
				"Trancados": 2,
				"Cancelados": 0,
				"MediaGeral": 4.29,
				"TaxadeAprovacao": 46.51,
				"TaxadeAprovacaoLiquida": 48.78,
				"MargemDeAprovacaoLiquida": 2.27
			},
			"programacao_paralela": {
				"nome": "Programacao Paralela",
				"Matriculados": 0,
				"Aprovados": 0,
				"Reprovados": 0,
				"Trancados": 0,
				"Cancelados": 0,
				"MediaGeral": 0,
				"TaxadeAprovacao": 0,
				"TaxadeAprovacaoLiquida": 0,
				"MargemDeAprovacaoLiquida": 0
			},
			"PAA": {
				"nome": "Projeto e Analise de Algoritmos",
				"Matriculados": 55,
				"Aprovados": 12,
				"Reprovados": 36,
				"Trancados": 3,
				"Cancelados": 4,
				"MediaGeral": 2.46,
				"TaxadeAprovacao": 23.53,
				"TaxadeAprovacaoLiquida": 25,
				"MargemDeAprovacaoLiquida": 1.47
			},
			"redes_computadores": {
				"nome": "Redes de Computadores",
				"Matriculados": 0,
				"Aprovados": 0,
				"Reprovados": 0,
				"Trancados": 0,
				"Cancelados": 0,
				"MediaGeral": 0,
				"TaxadeAprovacao": 0,
				"TaxadeAprovacaoLiquida": 0,
				"MargemDeAprovacaoLiquida": 0
			},
			"seminarios_comp": {
				"nome": "Seminarios em Computacao",
				"Matriculados": 0,
				"Aprovados": 0,
				"Reprovados": 0,
				"Trancados": 0,
				"Cancelados": 0,
				"MediaGeral": 0,
				"TaxadeAprovacao": 0,
				"TaxadeAprovacaoLiquida": 0,
				"MargemDeAprovacaoLiquida": 0
			},
			"sistemas_distribuidos": {
				"nome": "Sistemas Distribuidos",
				"Matriculados": 17,
				"Aprovados": 3,
				"Reprovados": 8,
				"Trancados": 6,
				"Cancelados": 0,
				"MediaGeral": 2.21,
				"TaxadeAprovacao": 17.65,
				"TaxadeAprovacaoLiquida": 27.27,
				"MargemDeAprovacaoLiquida": 9.63
			},
			"sistemas_operacionais": {
				"nome": "Sistemas Operacionais",
				"Matriculados": 13,
				"Aprovados": 12,
				"Reprovados": 1,
				"Trancados": 0,
				"Cancelados": 0,
				"MediaGeral": 6.79,
				"TaxadeAprovacao": 92.31,
				"TaxadeAprovacaoLiquida": 92.31,
				"MargemDeAprovacaoLiquida": 0
			},
			"trabalho_conclusao_curso_um": {
				"nome": "Trabalho de Conclusao de Curso I",
				"Matriculados": 1,
				"Aprovados": 0,
				"Reprovados": 1,
				"Trancados": 0,
				"Cancelados": 0,
				"MediaGeral": 0,
				"TaxadeAprovacao": 0,
				"TaxadeAprovacaoLiquida": 0,
				"MargemDeAprovacaoLiquida": 0
			},
			"trabalho_conclusao_curso_dois": {
				"nome": "Trabalho de Conclusao de Curso II",
				"Matriculados": 7,
				"Aprovados": 6,
				"Reprovados": 0,
				"Trancados": 1,
				"Cancelados": 0,
				"MediaGeral": 9.78,
				"TaxadeAprovacao": 85.71,
				"TaxadeAprovacaoLiquida": 100,
				"MargemDeAprovacaoLiquida": 14.29
			}
		},
		"2019.1": {
			"pi": {
				"nome": "Programacao Imperativa",
				"Matriculados": 11,
				"Aprovados": 5,
				"Reprovados": 3,
				"Trancados": 0,
				"Cancelados": 3,
				"MediaGeral": 5.34,
				"TaxadeAprovacao": 62.5,
				"TaxadeAprovacaoLiquida": 62.5,
				"MargemDeAprovacaoLiquida": 0
			},
			"pf": {
				"nome": "Programacao Funcional",
				"Matriculados": 83,
				"Aprovados": 18,
				"Reprovados": 54,
				"Trancados": 9,
				"Cancelados": 2,
				"MediaGeral": 2.37,
				"TaxadeAprovacao": 22.22,
				"TaxadeAprovacaoLiquida": 25,
				"MargemDeAprovacaoLiquida": 2.78
			},
			"arqui_computadores": {
				"nome": "Arquitetura de Computadores",
				"Matriculados": 19,
				"Aprovados": 0,
				"Reprovados": 9,
				"Trancados": 1,
				"Cancelados": 0,
				"MediaGeral": 3.25,
				"TaxadeAprovacao": 47.37,
				"TaxadeAprovacaoLiquida": 50.00,
				"MargemDeAprovacaoLiquida": 2.63
			},
			"banco_dados_um": {
				"nome": "Banco de Dados I",
				"Matriculados": 18,
				"Aprovados": 14,
				"Reprovados": 4,
				"Trancados": 0,
				"Cancelados": 0,
				"MediaGeral": 5.65,
				"TaxadeAprovacao": 77.78,
				"TaxadeAprovacaoLiquida": 77.78,
				"MargemDeAprovacaoLiquida": 0.00
			},
			"compiladores": {
				"nome": "Compiladores",
				"Matriculados": 28,
				"Aprovados": 24,
				"Reprovados": 4,
				"Trancados": 0,
				"Cancelados": 0,
				"MediaGeral": 6.13,
				"TaxadeAprovacao": 85.71,
				"TaxadeAprovacaoLiquida": 85.71,
				"MargemDeAprovacaoLiquida": 0.00
			},
			"eng_software_um": {
				"nome": "Engenharia de Software I",
				"Matriculados": 28,
				"Aprovados": 15,
				"Reprovados": 9,
				"Trancados": 3,
				"Cancelados": 1,
				"MediaGeral": 4.50,
				"TaxadeAprovacao": 55.56,
				"TaxadeAprovacaoLiquida": 62.50,
				"MargemDeAprovacaoLiquida": 6.94
			},
			"eng_software_dois": {
				"nome": "Engenharia de Software II",
				"Matriculados": 12,
				"Aprovados": 7,
				"Reprovados": 3,
				"Trancados": 2,
				"Cancelados": 0,
				"MediaGeral": 4.84,
				"TaxadeAprovacao": 58.33,
				"TaxadeAprovacaoLiquida": 70.00,
				"MargemDeAprovacaoLiquida": 11.67
			},

			"estagio_supervisionado_compu": {
				"nome": "Estagio Supervisionado em Computacao",
				"Matriculados": 13,
				"Aprovados": 13,
				"Reprovados": 0,
				"Trancados": 0,
				"Cancelados": 0,
				"MediaGeral": 9.77,
				"TaxadeAprovacao": 100,
				"TaxadeAprovacaoLiquida": 100,
				"MargemDeAprovacaoLiquida": 0
			},
			
			"ED": {
				"nome": "Estrutura de Dados",
				"Matriculados": 25,
				"Aprovados": 8,
				"Reprovados": 15,
				"Trancados": 2,
				"Cancelados": 0,
				"MediaGeral": 3.11,
				"TaxadeAprovacao": 32.00,
				"TaxadeAprovacaoLiquida": 34.78,
				"MargemDeAprovacaoLiquida": 2.78
			},
			"fundamentos_sistemas_digitais": {
				"nome": "Fundamentos de Sistemas Digitais",
				"Matriculados": 49,
				"Aprovados": 38,
				"Reprovados": 9,
				"Trancados": 2,
				"Cancelados": 0,
				"MediaGeral": 6.77,
				"TaxadeAprovacao": 77.55,
				"TaxadeAprovacaoLiquida": 80.85,
				"MargemDeAprovacaoLiquida": 3.30
			},

			"fundamentos_sistemas_embarcados": {
				"nome": "Fundamentos de Sistemas Embarcados",
				"Matriculados": 0,
				"Aprovados": 0,
				"Reprovados": 0,
				"Trancados": 0,
				"Cancelados": 0,
				"MediaGeral": 0,
				"TaxadeAprovacao": 0,
				"TaxadeAprovacaoLiquida": 0,
				"MargemDeAprovacaoLiquida": 0
			},
			"grafos": {
				"nome": "Grafos e Algoritmos Computacionais",
				"Matriculados": 27,
				"Aprovados": 11,
				"Reprovados": 12,
				"Trancados": 3,
				"Cancelados": 1,
				"MediaGeral": 3.68,
				"TaxadeAprovacao": 42.31,
				"TaxadeAprovacaoLiquida": 47.83,
				"MargemDeAprovacaoLiquida": 5.52
			},
			"informatica_et_socie": {
				"nome": "Informatica, Etica e Sociedade",
				"Matriculados": 57,
				"Aprovados": 40,
				"Reprovados": 8,
				"Trancados": 7,
				"Cancelados": 2,
				"MediaGeral": 7.27,
				"TaxadeAprovacao": 72.73,
				"TaxadeAprovacaoLiquida": 83.33,
				"MargemDeAprovacaoLiquida": 10.61
			},
			"inteligencia_artificial": {
				"nome": "Inteligencia Artificial",
				"Matriculados": 8,
				"Aprovados": 5,
				"Reprovados": 1,
				"Trancados": 2,
				"Cancelados": 0,
				"MediaGeral": 7.25,
				"TaxadeAprovacao": 62.50,
				"TaxadeAprovacaoLiquida": 83.33,
				"MargemDeAprovacaoLiquida": 20.83
			},
			"interface_hardware_software": {
				"nome": "Interface Hardware Software",
				"Matriculados": 16,
				"Aprovados": 5,
				"Reprovados": 10,
				"Trancados": 1,
				"Cancelados": 0,
				"MediaGeral": 3.23,
				"TaxadeAprovacao": 31.25,
				"TaxadeAprovacaoLiquida": 33.33,
				"MargemDeAprovacaoLiquida": 2.08
			},
			"laboratorio_redes_computadores": {
				"nome": "Laboratorio de Redes de Computadores",
				"Matriculados": 5,
				"Aprovados": 1,
				"Reprovados": 2,
				"Trancados": 0,
				"Cancelados": 2,
				"MediaGeral": 2.70,
				"TaxadeAprovacao": 33.33,
				"TaxadeAprovacaoLiquida": 33.33,
				"MargemDeAprovacaoLiquida": 0
			},
			"LFC": {
				"nome": "Linguagens Formais e Computabilidade",
				"Matriculados": 38,
				"Aprovados": 14,
				"Reprovados": 20,
				"Trancados": 4,
				"Cancelados": 0,
				"MediaGeral": 3.31,
				"TaxadeAprovacao": 36.84,
				"TaxadeAprovacaoLiquida": 41.18,
				"MargemDeAprovacaoLiquida": 4.33
			},
			"logica_computacao": {
				"nome": "Logica de Computacao",
				"Matriculados": 6,
				"Aprovados": 3,
				"Reprovados": 3,
				"Trancados": 0,
				"Cancelados": 0,
				"MediaGeral": 2.68,
				"TaxadeAprovacao": 50.00,
				"TaxadeAprovacaoLiquida": 50.00,
				"MargemDeAprovacaoLiquida": 0.00
			},
			"metodos_tecnicas_pesquisa_compu": {
				"nome": "Metodos e Tecnicas de Pesquisa para Computacao",
				"Matriculados": 25,
				"Aprovados": 21,
				"Reprovados": 4,
				"Trancados": 0,
				"Cancelados": 0,
				"MediaGeral": 6.31,
				"TaxadeAprovacao": 84.00,
				"TaxadeAprovacaoLiquida": 84.00,
				"MargemDeAprovacaoLiquida": 0.00
			},
			"pratica_sistemas_digi": {
				"nome": "Praticas em Sistemas Digitais",
				"Matriculados": 31,
				"Aprovados": 24,
				"Reprovados": 7,
				"Trancados": 0,
				"Cancelados": 0,
				"MediaGeral": 7.17,
				"TaxadeAprovacao": 77.42,
				"TaxadeAprovacaoLiquida": 77.42,
				"MargemDeAprovacaoLiquida": 0.00
			},
			"pratica_orientada_em_comp_um": {
				"nome": "Pratica Orientada em Computacao I",
				"Matriculados": 13,
				"Aprovados": 11,
				"Reprovados": 1,
				"Trancados": 1,
				"Cancelados": 0,
				"MediaGeral": 7.46,
				"TaxadeAprovacao": 84.00,
				"TaxadeAprovacaoLiquida": 91.46,
				"MargemDeAprovacaoLiquida": 7.46
			},
			"pratica_orientada_em_comp_dois": {
				"nome": "Pratica Orientada em Computacao II",
				"Matriculados": 5,
				"Aprovados": 3,
				"Reprovados": 0,
				"Trancados": 2,
				"Cancelados": 0,
				"MediaGeral": 6.73,
				"TaxadeAprovacao": 60,
				"TaxadeAprovacaoLiquida": 100,
				"MargemDeAprovacaoLiquida": 40
			},
			"POO": {
				"nome": "Programacao Orientada a Objetos",
				"Matriculados": 47,
				"Aprovados": 23,
				"Reprovados": 18,
				"Trancados": 6,
				"Cancelados": 0,
				"MediaGeral": 4.16,
				"TaxadeAprovacao": 48.94,
				"TaxadeAprovacaoLiquida": 56.10,
				"MargemDeAprovacaoLiquida": 7.16
			},
			"programacao_paralela": {
				"nome": "Programacao Paralela",
				"Matriculados": 0,
				"Aprovados": 0,
				"Reprovados": 0,
				"Trancados": 0,
				"Cancelados": 0,
				"MediaGeral": 0,
				"TaxadeAprovacao": 0,
				"TaxadeAprovacaoLiquida": 0,
				"MargemDeAprovacaoLiquida": 0
			},

			"PAA": {
				"nome": "Projeto e Analise de Algoritmos",
				"Matriculados": 0,
				"Aprovados": 0,
				"Reprovados": 0,
				"Trancados": 0,
				"Cancelados": 0,
				"MediaGeral": 0,
				"TaxadeAprovacao": 0,
				"TaxadeAprovacaoLiquida": 0,
				"MargemDeAprovacaoLiquida": 0
			},
			"redes_computadores": {
				"nome": "Redes de Computadores",
				"Matriculados": 24,
				"Aprovados": 15,
				"Reprovados": 8,
				"Trancados": 1,
				"Cancelados": 0,
				"MediaGeral": 4.72,
				"TaxadeAprovacao": 62.50,
				"TaxadeAprovacaoLiquida": 65.22,
				"MargemDeAprovacaoLiquida": 2.72
			},
			"seminarios_comp": {
				"nome": "Seminarios em Computacao",
				"Matriculados": 57,
				"Aprovados": 51,
				"Reprovados": 4,
				"Trancados": 0,
				"Cancelados": 2,
				"MediaGeral": 8.75,
				"TaxadeAprovacao": 92.73,
				"TaxadeAprovacaoLiquida": 92.73,
				"MargemDeAprovacaoLiquida": 0.0
			},
			"sistemas_distribuidos": {
				"nome": "Sistemas Distribuidos",
				"Matriculados": 0,
				"Aprovados": 0,
				"Reprovados": 0,
				"Trancados": 0,
				"Cancelados": 0,
				"MediaGeral": 0,
				"TaxadeAprovacao": 0,
				"TaxadeAprovacaoLiquida": 0,
				"MargemDeAprovacaoLiquida": 0
			},
			"sistemas_operacionais": {
				"nome": "Sistemas Operacionais",
				"Matriculados": 39,
				"Aprovados": 28,
				"Reprovados": 9,
				"Trancados": 2,
				"Cancelados": 0,
				"MediaGeral": 5.21,
				"TaxadeAprovacao": 71.79,
				"TaxadeAprovacaoLiquida": 75.68,
				"MargemDeAprovacaoLiquida": 3.88
			},
			"trabalho_conclusao_curso_um": {
				"nome": "Trabalho de Conclusao de Curso I",
				"Matriculados": 3,
				"Aprovados": 3,
				"Reprovados": 0,
				"Trancados": 0,
				"Cancelados": 0,
				"MediaGeral": 8.50,
				"TaxadeAprovacao": 100,
				"TaxadeAprovacaoLiquida": 100,
				"MargemDeAprovacaoLiquida": 0
			},
			"trabalho_conclusao_curso_dois": {
				"nome": "Trabalho de Conclusao de Curso II",
				"Matriculados": 12,
				"Aprovados": 6,
				"Reprovados": 6,
				"Trancados": 0,
				"Cancelados": 0,
				"MediaGeral": 5.57,
				"TaxadeAprovacao": 50,
				"TaxadeAprovacaoLiquida": 50,
				"MargemDeAprovacaoLiquida": 0
			}
		},
		"2019.2": {
			"pi": {
				"nome": "Programacao Imperativa",
				"Matriculados": 56,
				"Aprovados": 37,
				"Reprovados": 15,
				"Trancados": 2,
				"Cancelados": 2,
				"MediaGeral": 5.48,
				"TaxadeAprovacao": 68.52,
				"TaxadeAprovacaoLiquida": 71.15,
				"MargemDeAprovacaoLiquida": 2.64
			},
			"pf": {
				"nome": "Programacao Funcional",
				"Matriculados": 71,
				"Aprovados": 36,
				"Reprovados": 31,
				"Trancados": 4,
				"Cancelados": 0,
				"MediaGeral": 3.94,
				"TaxadeAprovacao": 50.7,
				"TaxadeAprovacaoLiquida": 53.73,
				"MargemDeAprovacaoLiquida": 3.03
			},
			"arqui_computadores": {
				"nome": "Arquitetura de Computadores",
				"Matriculados": 55,
				"Aprovados": 33,
				"Reprovados": 12,
				"Trancados": 10,
				"Cancelados": 0,
				"MediaGeral": 5.83,
				"TaxadeAprovacao": 60,
				"TaxadeAprovacaoLiquida": 73.33,
				"MargemDeAprovacaoLiquida": 13.33
			},
			"banco_dados_um": {
				"nome": "Banco de Dados I",
				"Matriculados": 24,
				"Aprovados": 16,
				"Reprovados": 6,
				"Trancados": 1,
				"Cancelados": 1,
				"MediaGeral": 5.74,
				"TaxadeAprovacao": 69.57,
				"TaxadeAprovacaoLiquida": 72.73,
				"MargemDeAprovacaoLiquida": 3.16
			},
			"compiladores": {
				"nome": "Compiladores",
				"Matriculados": 13,
				"Aprovados": 9,
				"Reprovados": 4,
				"Trancados": 0,
				"Cancelados": 0,
				"MediaGeral": 5.32,
				"TaxadeAprovacao": 69.23,
				"TaxadeAprovacaoLiquida": 69.23,
				"MargemDeAprovacaoLiquida": 0.00
			},
			"eng_software_um": {
				"nome": "Engenharia de Software I",
				"Matriculados": 0,
				"Aprovados": 0,
				"Reprovados": 0,
				"Trancados": 0,
				"Cancelados": 0,
				"MediaGeral": 0,
				"TaxadeAprovacao": 0,
				"TaxadeAprovacaoLiquida": 0,
				"MargemDeAprovacaoLiquida": 0
			},
			"eng_software_dois": {
				"nome": "Engenharia de Software II",
				"Matriculados": 30,
				"Aprovados": 16,
				"Reprovados": 12,
				"Trancados": 2,
				"Cancelados": 0,
				"MediaGeral": 3.80,
				"TaxadeAprovacao": 53.33,
				"TaxadeAprovacaoLiquida": 57.14,
				"MargemDeAprovacaoLiquida": 3.81
			},

			"estagio_supervisionado_compu": {
				"nome": "Estagio Supervisionado em Computacao",
				"Matriculados": 16,
				"Aprovados": 14,
				"Reprovados": 0,
				"Trancados": 0,
				"Cancelados": 0,
				"MediaGeral": 10,
				"TaxadeAprovacao": 87.50,
				"TaxadeAprovacaoLiquida": 87.50,
				"MargemDeAprovacaoLiquida": 0
			},

			"ED": {
				"nome": "Estrutura de Dados",
				"Matriculados": 16,
				"Aprovados": 0,
				"Reprovados": 12,
				"Trancados": 4,
				"Cancelados": 0,
				"MediaGeral": 1.36,
				"TaxadeAprovacao": 0,
				"TaxadeAprovacaoLiquida": 0,
				"MargemDeAprovacaoLiquida": 0
			},
			"fundamentos_sistemas_digitais": {
				"nome": "Fundamentos de Sistemas Digitais",
				"Matriculados": 5,
				"Aprovados": 1,
				"Reprovados": 4,
				"Trancados": 0,
				"Cancelados": 0,
				"MediaGeral": 2.12,
				"TaxadeAprovacao": 20,
				"TaxadeAprovacaoLiquida": 20,
				"MargemDeAprovacaoLiquida": 0
			},
			"fundamentos_sistemas_embarcados": {
				"nome": "Fundamentos de Sistemas Embarcados",
				"Matriculados": 42,
				"Aprovados": 15,
				"Reprovados": 23,
				"Trancados": 4,
				"Cancelados": 0,
				"MediaGeral": 2.67,
				"TaxadeAprovacao": 35.71,
				"TaxadeAprovacaoLiquida": 39.47,
				"MargemDeAprovacaoLiquida": 3.76
			},
			"grafos": {
				"nome": "Grafos e Algoritmos Computacionais",
				"Matriculados": 29,
				"Aprovados": 22,
				"Reprovados": 5,
				"Trancados": 2,
				"Cancelados": 0,
				"MediaGeral": 5.91,
				"TaxadeAprovacao": 75.86,
				"TaxadeAprovacaoLiquida": 81.48,
				"MargemDeAprovacaoLiquida": 5.62
			},
			"informatica_et_socie": {
				"nome": "Informatica, Etica e Sociedade",
				"Matriculados": 11,
				"Aprovados": 4,
				"Reprovados": 4,
				"Trancados": 3,
				"Cancelados": 0,
				"MediaGeral": 4.41,
				"TaxadeAprovacao": 36.36,
				"TaxadeAprovacaoLiquida": 50,
				"MargemDeAprovacaoLiquida": 13.64
			},
			"inteligencia_artificial": {
				"nome": "Inteligencia Artificial",
				"Matriculados": 23,
				"Aprovados": 15,
				"Reprovados": 7,
				"Trancados": 1,
				"Cancelados": 0,
				"MediaGeral": 5.77,
				"TaxadeAprovacao": 65.22,
				"TaxadeAprovacaoLiquida": 68.18,
				"MargemDeAprovacaoLiquida": 2.96
			},
			"interface_hardware_software": {
				"nome": "Interface Hardware Software",
				"Matriculados": 1,
				"Aprovados": 1,
				"Reprovados": 0,
				"Trancados": 0,
				"Cancelados": 0,
				"MediaGeral": 5,
				"TaxadeAprovacao": 100,
				"TaxadeAprovacaoLiquida": 100,
				"MargemDeAprovacaoLiquida": 0
			},
			"laboratorio_redes_computadores": {
				"nome": "Laboratorio de Redes de Computadores",
				"Matriculados": 22,
				"Aprovados": 15,
				"Reprovados": 6,
				"Trancados": 1,
				"Cancelados": 0,
				"MediaGeral": 6.08,
				"TaxadeAprovacao": 68.18,
				"TaxadeAprovacaoLiquida": 71.43,
				"MargemDeAprovacaoLiquida": 3.25
			},
			"LFC": {
				"nome": "Linguagens Formais e Computabilidade",
				"Matriculados": 27,
				"Aprovados": 18,
				"Reprovados": 9,
				"Trancados": 0,
				"Cancelados": 0,
				"MediaGeral": 5.11,
				"TaxadeAprovacao": 66.67,
				"TaxadeAprovacaoLiquida": 66.67,
				"MargemDeAprovacaoLiquida": 0
			},
			"logica_computacao": {
				"nome": "Logica de Computacao",
				"Matriculados": 41,
				"Aprovados": 33,
				"Reprovados": 7,
				"Trancados": 0,
				"Cancelados": 1,
				"MediaGeral": 6,
				"TaxadeAprovacao": 82.50,
				"TaxadeAprovacaoLiquida": 82.50,
				"MargemDeAprovacaoLiquida": 0.00
			},
			"metodos_tecnicas_pesquisa_compu": {
				"nome": "Metodos e Tecnicas de Pesquisa para Computacao",
				"Matriculados": 23,
				"Aprovados": 12,
				"Reprovados": 10,
				"Trancados": 1,
				"Cancelados": 0,
				"MediaGeral": 4.57,
				"TaxadeAprovacao": 52.17,
				"TaxadeAprovacaoLiquida": 54.55,
				"MargemDeAprovacaoLiquida": 2.37
			},
			"pratica_sistemas_digi": {
				"nome": "Praticas em Sistemas Digitais",
				"Matriculados": 17,
				"Aprovados": 12,
				"Reprovados": 5,
				"Trancados": 0,
				"Cancelados": 0,
				"MediaGeral": 6.84,
				"TaxadeAprovacao": 70.59,
				"TaxadeAprovacaoLiquida": 70.59,
				"MargemDeAprovacaoLiquida": 0.00
			},
			"pratica_orientada_em_comp_um": {
				"nome": "Pratica Orientada em Computacao I",
				"Matriculados": 4,
				"Aprovados": 4,
				"Reprovados": 0,
				"Trancados": 0,
				"Cancelados": 0,
				"MediaGeral": 6.70,
				"TaxadeAprovacao": 100,
				"TaxadeAprovacaoLiquida": 100,
				"MargemDeAprovacaoLiquida": 0
			},
			"pratica_orientada_em_comp_dois": {
				"nome": "Pratica Orientada em Computacao II",
				"Matriculados": 11,
				"Aprovados": 11,
				"Reprovados": 0,
				"Trancados": 0,
				"Cancelados": 0,
				"MediaGeral": 8.03,
				"TaxadeAprovacao": 100,
				"TaxadeAprovacaoLiquida": 100,
				"MargemDeAprovacaoLiquida": 0
			},
			"POO": {
				"nome": "Programacao Orientada a Objetos",
				"Matriculados": 19,
				"Aprovados": 6,
				"Reprovados": 13,
				"Trancados": 0,
				"Cancelados": 0,
				"MediaGeral": 2.14,
				"TaxadeAprovacao": 31.58,
				"TaxadeAprovacaoLiquida": 31.58,
				"MargemDeAprovacaoLiquida": 0
			},
			"programacao_paralela": {
				"nome": "Programacao Paralela",
				"Matriculados": 0,
				"Aprovados": 0,
				"Reprovados": 0,
				"Trancados": 0,
				"Cancelados": 0,
				"MediaGeral": 0,
				"TaxadeAprovacao": 0,
				"TaxadeAprovacaoLiquida": 0,
				"MargemDeAprovacaoLiquida": 0
			},
			"PAA": {
				"nome": "Projeto e Analise de Algoritmos",
				"Matriculados": 37,
				"Aprovados": 8,
				"Reprovados": 22,
				"Trancados": 7,
				"Cancelados": 0,
				"MediaGeral": 2.23,
				"TaxadeAprovacao": 21.62,
				"TaxadeAprovacaoLiquida": 26.67,
				"MargemDeAprovacaoLiquida": 5.05
			},
			"redes_computadores": {
				"nome": "Redes de Computadores",
				"Matriculados": 14,
				"Aprovados": 10,
				"Reprovados": 4,
				"Trancados": 0,
				"Cancelados": 0,
				"MediaGeral": 5.40,
				"TaxadeAprovacao": 71.43,
				"TaxadeAprovacaoLiquida": 71.43,
				"MargemDeAprovacaoLiquida": 0
			},
			"seminarios_comp": {
				"nome": "Seminarios em Computacao",
				"Matriculados": 0,
				"Aprovados": 0,
				"Reprovados": 0,
				"Trancados": 0,
				"Cancelados": 0,
				"MediaGeral": 0,
				"TaxadeAprovacao": 0,
				"TaxadeAprovacaoLiquida": 0,
				"MargemDeAprovacaoLiquida": 0
			},
			"sistemas_distribuidos": {
				"nome": "Sistemas Distribuidos",
				"Matriculados": 17,
				"Aprovados": 10,
				"Reprovados": 7,
				"Trancados": 0,
				"Cancelados": 0,
				"MediaGeral": 5.44,
				"TaxadeAprovacao": 58.82,
				"TaxadeAprovacaoLiquida": 58.82,
				"MargemDeAprovacaoLiquida": 0
			},
			"sistemas_operacionais": {
				"nome": "Sistemas Operacionais",
				"Matriculados": 10,
				"Aprovados": 6,
				"Reprovados": 1,
				"Trancados": 3,
				"Cancelados": 0,
				"MediaGeral": 4.93,
				"TaxadeAprovacao": 60,
				"TaxadeAprovacaoLiquida": 85.71,
				"MargemDeAprovacaoLiquida": 25.71
			},
			"trabalho_conclusao_curso_um": {
				"nome": "Trabalho de Conclusao de Curso I",
				"Matriculados": 8,
				"Aprovados": 5,
				"Reprovados": 3,
				"Trancados": 0,
				"Cancelados": 0,
				"MediaGeral": 5.56,
				"TaxadeAprovacao": 62.50,
				"TaxadeAprovacaoLiquida": 62.50,
				"MargemDeAprovacaoLiquida": 0
			},
			"trabalho_conclusao_curso_dois": {
				"nome": "Trabalho de Conclusao de Curso II",
				"Matriculados": 18,
				"Aprovados": 11,
				"Reprovados": 7,
				"Trancados": 0,
				"Cancelados": 0,
				"MediaGeral": 6.47,
				"TaxadeAprovacao": 61.11,
				"TaxadeAprovacaoLiquida": 61.11,
				"MargemDeAprovacaoLiquida": 0
			}
		},
		"2020.1": {
			"pi": {
				"nome": "Programacao Imperativa",
				"Matriculados": 8,
				"Aprovados": 3,
				"Reprovados": 5,
				"Trancados": 0,
				"Cancelados": 0,
				"MediaGeral": 2.88,
				"TaxadeAprovacao": 37.5,
				"TaxadeAprovacaoLiquida": 37.5,
				"MargemDeAprovacaoLiquida": 0
			},
			"pf": {
				"nome": "Programacao Funcional",
				"Matriculados": 71,
				"Aprovados": 39,
				"Reprovados": 23,
				"Trancados": 7,
				"Cancelados": 2,
				"MediaGeral": 5.04,
				"TaxadeAprovacao": 56.52,
				"TaxadeAprovacaoLiquida": 62.9,
				"MargemDeAprovacaoLiquida": 6.38
			},
			"arqui_computadores": {
				"nome": "Arquitetura de Computadores",
				"Matriculados": 21,
				"Aprovados": 6,
				"Reprovados": 6,
				"Trancados": 9,
				"Cancelados": 0,
				"MediaGeral": 3.92,
				"TaxadeAprovacao": 28.57,
				"TaxadeAprovacaoLiquida": 50,
				"MargemDeAprovacaoLiquida": 21.43
			},
			"banco_dados_um": {
				"nome": "Banco de Dados I",
				"Matriculados": 9,
				"Aprovados": 3,
				"Reprovados": 5,
				"Trancados": 1,
				"Cancelados": 0,
				"MediaGeral": 3.91,
				"TaxadeAprovacao": 33.33,
				"TaxadeAprovacaoLiquida": 37.50,
				"MargemDeAprovacaoLiquida": 4.17
			},
			"compiladores": {
				"nome": "Compiladores",
				"Matriculados": 12,
				"Aprovados": 8,
				"Reprovados": 4,
				"Trancados": 0,
				"Cancelados": 0,
				"MediaGeral": 5.43,
				"TaxadeAprovacao": 66.67,
				"TaxadeAprovacaoLiquida": 66.67,
				"MargemDeAprovacaoLiquida": 0
			},
			"eng_software_um": {
				"nome": "Engenharia de Software I",
				"Matriculados": 38,
				"Aprovados": 24,
				"Reprovados": 12,
				"Trancados": 2,
				"Cancelados": 0,
				"MediaGeral": 4.99,
				"TaxadeAprovacao": 63.16,
				"TaxadeAprovacaoLiquida": 66.67,
				"MargemDeAprovacaoLiquida": 3.51
			},
			"eng_software_dois": {
				"nome": "Engenharia de Software II",
				"Matriculados": 0,
				"Aprovados": 0,
				"Reprovados": 0,
				"Trancados": 0,
				"Cancelados": 0,
				"MediaGeral": 0,
				"TaxadeAprovacao": 0,
				"TaxadeAprovacaoLiquida": 0,
				"MargemDeAprovacaoLiquida": 0
			},

			"estagio_supervisionado_compu": {
				"nome": "Estagio Supervisionado em Computacao",
				"Matriculados": 9,
				"Aprovados": 7,
				"Reprovados": 0,
				"Trancados": 0,
				"Cancelados": 1,
				"MediaGeral": 9.93,
				"TaxadeAprovacao": 87.50,
				"TaxadeAprovacaoLiquida": 87.50,
				"MargemDeAprovacaoLiquida": 0
			},

			"ED": {
				"nome": "Estrutura de Dados",
				"Matriculados": 39,
				"Aprovados": 22,
				"Reprovados": 13,
				"Trancados": 4,
				"Cancelados": 0,
				"MediaGeral": 5.44,
				"TaxadeAprovacao": 56.41,
				"TaxadeAprovacaoLiquida": 62.86,
				"MargemDeAprovacaoLiquida": 6.45
			},
			"fundamentos_sistemas_digitais": {
				"nome": "Fundamentos de Sistemas Digitais",
				"Matriculados": 50,
				"Aprovados": 32,
				"Reprovados": 14,
				"Trancados": 4,
				"Cancelados": 0,
				"MediaGeral": 6.03,
				"TaxadeAprovacao": 64,
				"TaxadeAprovacaoLiquida": 69.57,
				"MargemDeAprovacaoLiquida": 5.57
			},
			"fundamentos_sistemas_embarcados": {
				"nome": "Fundamentos de Sistemas Embarcados",
				"Matriculados": 0,
				"Aprovados": 0,
				"Reprovados": 0,
				"Trancados": 0,
				"Cancelados": 0,
				"MediaGeral": 0,
				"TaxadeAprovacao": 0,
				"TaxadeAprovacaoLiquida": 0,
				"MargemDeAprovacaoLiquida": 0
			},
			"grafos": {
				"nome": "Grafos e Algoritmos Computacionais",
				"Matriculados": 14,
				"Aprovados": 9,
				"Reprovados": 5,
				"Trancados": 0,
				"Cancelados": 0,
				"MediaGeral": 4.84,
				"TaxadeAprovacao": 64.29,
				"TaxadeAprovacaoLiquida": 64.29,
				"MargemDeAprovacaoLiquida": 0
			},
			"informatica_et_socie": {
				"nome": "Informatica, Etica e Sociedade",
				"Matriculados": 63,
				"Aprovados": 43,
				"Reprovados": 10,
				"Trancados": 8,
				"Cancelados": 2,
				"MediaGeral": 7.78,
				"TaxadeAprovacao": 70.49,
				"TaxadeAprovacaoLiquida": 81.13,
				"MargemDeAprovacaoLiquida": 10.64
			},
			"inteligencia_artificial": {
				"nome": "Inteligencia Artificial",
				"Matriculados": 0,
				"Aprovados": 0,
				"Reprovados": 0,
				"Trancados": 0,
				"Cancelados": 0,
				"MediaGeral": 0,
				"TaxadeAprovacao": 0,
				"TaxadeAprovacaoLiquida": 0,
				"MargemDeAprovacaoLiquida": 0
			},
			"interface_hardware_software": {
				"nome": "Interface Hardware Software",
				"Matriculados": 33,
				"Aprovados": 10,
				"Reprovados": 12,
				"Trancados": 11,
				"Cancelados": 0,
				"MediaGeral": 3.65,
				"TaxadeAprovacao": 30.30,
				"TaxadeAprovacaoLiquida": 45.45,
				"MargemDeAprovacaoLiquida": 15.15
			},
			"laboratorio_redes_computadores": {
				"nome": "Laboratorio de Redes de Computadores",
				"Matriculados": 0,
				"Aprovados": 0,
				"Reprovados": 0,
				"Trancados": 0,
				"Cancelados": 0,
				"MediaGeral": 0,
				"TaxadeAprovacao": 0,
				"TaxadeAprovacaoLiquida": 0,
				"MargemDeAprovacaoLiquida": 0
			},
			"LFC": {
				"nome": "Linguagens Formais e Computabilidade",
				"Matriculados": 34,
				"Aprovados": 24,
				"Reprovados": 9,
				"Trancados": 1,
				"Cancelados": 0,
				"MediaGeral": 4.97,
				"TaxadeAprovacao": 70.59,
				"TaxadeAprovacaoLiquida": 72.73,
				"MargemDeAprovacaoLiquida": 2.14
			},
			"logica_computacao": {
				"nome": "Logica de Computacao",
				"Matriculados": 10,
				"Aprovados": 5,
				"Reprovados": 5,
				"Trancados": 0,
				"Cancelados": 0,
				"MediaGeral": 4.12,
				"TaxadeAprovacao": 50,
				"TaxadeAprovacaoLiquida": 50,
				"MargemDeAprovacaoLiquida": 0
			},
			"metodos_tecnicas_pesquisa_compu": {
				"nome": "Metodos e Tecnicas de Pesquisa para Computacao",
				"Matriculados": 35,
				"Aprovados": 32,
				"Reprovados": 2,
				"Trancados": 1,
				"Cancelados": 0,
				"MediaGeral": 7.64,
				"TaxadeAprovacao": 91.43,
				"TaxadeAprovacaoLiquida": 94.12,
				"MargemDeAprovacaoLiquida": 2.69
			},
			"pratica_sistemas_digi": {
				"nome": "Praticas em Sistemas Digitais",
				"Matriculados": 49,
				"Aprovados": 30,
				"Reprovados": 16,
				"Trancados": 3,
				"Cancelados": 0,
				"MediaGeral": 5.12,
				"TaxadeAprovacao": 61.22,
				"TaxadeAprovacaoLiquida": 65.22,
				"MargemDeAprovacaoLiquida": 3.99
			},
			"pratica_orientada_em_comp_um": {
				"nome": "Pratica Orientada em Computacao I",
				"Matriculados": 18,
				"Aprovados": 12,
				"Reprovados": 4,
				"Trancados": 2,
				"Cancelados": 0,
				"MediaGeral": 7.56,
				"TaxadeAprovacao": 66.67,
				"TaxadeAprovacaoLiquida": 75,
				"MargemDeAprovacaoLiquida": 8.33
			},
			"pratica_orientada_em_comp_dois": {
				"nome": "Pratica Orientada em Computacao II",
				"Matriculados": 2,
				"Aprovados": 2,
				"Reprovados": 0,
				"Trancados": 0,
				"Cancelados": 0,
				"MediaGeral": 9,
				"TaxadeAprovacao": 100,
				"TaxadeAprovacaoLiquida": 100,
				"MargemDeAprovacaoLiquida": 0
			},
			"POO": {
				"nome": "Programacao Orientada a Objetos",
				"Matriculados": 62,
				"Aprovados": 22,
				"Reprovados": 27,
				"Trancados": 13,
				"Cancelados": 0,
				"MediaGeral": 4.14,
				"TaxadeAprovacao": 35.48,
				"TaxadeAprovacaoLiquida": 49.90,
				"MargemDeAprovacaoLiquida": 9.41
			},
			"programacao_paralela": {
				"nome": "Programacao Paralela",
				"Matriculados": 0,
				"Aprovados": 0,
				"Reprovados": 0,
				"Trancados": 0,
				"Cancelados": 0,
				"MediaGeral": 0,
				"TaxadeAprovacao": 0,
				"TaxadeAprovacaoLiquida": 0,
				"MargemDeAprovacaoLiquida": 0
			},
			"PAA": {
				"nome": "Projeto e Analise de Algoritmos",
				"Matriculados": 0,
				"Aprovados": 0,
				"Reprovados": 0,
				"Trancados": 0,
				"Cancelados": 0,
				"MediaGeral": 0,
				"TaxadeAprovacao": 0,
				"TaxadeAprovacaoLiquida": 0,
				"MargemDeAprovacaoLiquida": 0
			},
			"redes_computadores": {
				"nome": "Redes de Computadores",
				"Matriculados": 33,
				"Aprovados": 26,
				"Reprovados": 7,
				"Trancados": 0,
				"Cancelados": 0,
				"MediaGeral": 5.61,
				"TaxadeAprovacao": 78.79,
				"TaxadeAprovacaoLiquida": 78.79,
				"MargemDeAprovacaoLiquida": 0
			},
			"seminarios_comp": {
				"nome": "Seminarios em Computacao",
				"Matriculados": 62,
				"Aprovados": 53,
				"Reprovados": 2,
				"Trancados": 5,
				"Cancelados": 2,
				"MediaGeral": 9.22,
				"TaxadeAprovacao": 88.33,
				"TaxadeAprovacaoLiquida": 96.36,
				"MargemDeAprovacaoLiquida": 8.03
			},
			"sistemas_distribuidos": {
				"nome": "Sistemas Distribuidos",
				"Matriculados": 15,
				"Aprovados": 13,
				"Reprovados": 2,
				"Trancados": 0,
				"Cancelados": 0,
				"MediaGeral": 7.39,
				"TaxadeAprovacao": 86.67,
				"TaxadeAprovacaoLiquida": 86.67,
				"MargemDeAprovacaoLiquida": 0
			},
			"sistemas_operacionais": {
				"nome": "Sistemas Operacionais",
				"Matriculados": 17,
				"Aprovados": 14,
				"Reprovados": 3,
				"Trancados": 0,
				"Cancelados": 0,
				"MediaGeral": 7.19,
				"TaxadeAprovacao": 82.35,
				"TaxadeAprovacaoLiquida": 85.35,
				"MargemDeAprovacaoLiquida": 0
			},
			"trabalho_conclusao_curso_um": {
				"nome": "Trabalho de Conclusao de Curso I",
				"Matriculados": 1,
				"Aprovados": 1,
				"Reprovados": 0,
				"Trancados": 0,
				"Cancelados": 0,
				"MediaGeral": 6,
				"TaxadeAprovacao": 100,
				"TaxadeAprovacaoLiquida": 100,
				"MargemDeAprovacaoLiquida": 0
			},
			"trabalho_conclusao_curso_dois": {
				"nome": "Trabalho de Conclusao de Curso II",
				"Matriculados": 6,
				"Aprovados": 2,
				"Reprovados": 4,
				"Trancados": 0,
				"Cancelados": 0,
				"MediaGeral": 4.60,
				"TaxadeAprovacao": 33.33,
				"TaxadeAprovacaoLiquida": 33.33,
				"MargemDeAprovacaoLiquida": 0
			}
			
		},
		"2020.2": {
			"pi": {
				"nome": "Programacao Imperativa",
				"Matriculados": 49,
				"Aprovados": 28,
				"Reprovados": 16,
				"Trancados": 4,
				"Cancelados": 1,
				"MediaGeral": 6.07,
				"TaxadeAprovacao": 58.33,
				"TaxadeAprovacaoLiquida": 63.64,
				"MargemDeAprovacaoLiquida": 5.30
			},
			"pf": {
				"nome": "Programacao Funcional",
				"Matriculados": 25,
				"Aprovados": 13,
				"Reprovados": 7,
				"Trancados": 5,
				"Cancelados": 0,
				"MediaGeral": 52,
				"TaxadeAprovacao": 55,
				"TaxadeAprovacaoLiquida": 65,
				"MargemDeAprovacaoLiquida": 13
			},
			"arqui_computadores": {
				"nome": "Arquitetura de Computadores",
				"Matriculados": 46,
				"Aprovados": 23,
				"Reprovados": 15,
				"Trancados": 8,
				"Cancelados": 0,
				"MediaGeral": 5.22,
				"TaxadeAprovacao": 50,
				"TaxadeAprovacaoLiquida": 60.53,
				"MargemDeAprovacaoLiquida": 10.53
			},
			"banco_dados_um": {
				"nome": "Banco de Dados I",
				"Matriculados": 8,
				"Aprovados": 7,
				"Reprovados": 0,
				"Trancados": 0,
				"Cancelados": 1,
				"MediaGeral": 7.17,
				"TaxadeAprovacao": 100,
				"TaxadeAprovacaoLiquida": 100,
				"MargemDeAprovacaoLiquida": 0
			},
			"compiladores": {
				"nome": "Compiladores",
				"Matriculados": 19,
				"Aprovados": 14,
				"Reprovados": 3,
				"Trancados": 0,
				"Cancelados": 2,
				"MediaGeral": 5.96,
				"TaxadeAprovacao": 82.35,
				"TaxadeAprovacaoLiquida": 82.35,
				"MargemDeAprovacaoLiquida": 0
			},
			"eng_software_um": {
				"nome": "Engenharia de Software I",
				"Matriculados": 26,
				"Aprovados": 11,
				"Reprovados": 6,
				"Trancados": 1,
				"Cancelados": 8,
				"MediaGeral": 5.33,
				"TaxadeAprovacao": 61.11,
				"TaxadeAprovacaoLiquida": 64.71,
				"MargemDeAprovacaoLiquida": 3.59
			},
			"eng_software_dois": {
				"nome": "Engenharia de Software II",
				"Matriculados": 19,
				"Aprovados": 16,
				"Reprovados": 1,
				"Trancados": 1,
				"Cancelados": 1,
				"MediaGeral": 6.69,
				"TaxadeAprovacao": 88.89,
				"TaxadeAprovacaoLiquida": 94.12,
				"MargemDeAprovacaoLiquida": 5.23
			},

			"estagio_supervisionado_compu": {
				"nome": "Estagio Supervisionado em Computacao",
				"Matriculados": 8,
				"Aprovados": 8,
				"Reprovados": 0,
				"Trancados": 0,
				"Cancelados": 0,
				"MediaGeral": 9.88,
				"TaxadeAprovacao": 100,
				"TaxadeAprovacaoLiquida": 100,
				"MargemDeAprovacaoLiquida": 0
			},

			"ED": {
				"nome": "Estrutura de Dados",
				"Matriculados": 34,
				"Aprovados": 18,
				"Reprovados": 10,
				"Trancados": 5,
				"Cancelados": 1,
				"MediaGeral": 5.29,
				"TaxadeAprovacao": 54.55,
				"TaxadeAprovacaoLiquida": 64.29,
				"MargemDeAprovacaoLiquida": 9.74
			},
			"fundamentos_sistemas_digitais": {
				"nome": "Fundamentos de Sistemas Digitais",
				"Matriculados": 13,
				"Aprovados": 9,
				"Reprovados": 4,
				"Trancados": 0,
				"Cancelados": 0,
				"MediaGeral": 6.97,
				"TaxadeAprovacao": 69.23,
				"TaxadeAprovacaoLiquida": 69.23,
				"MargemDeAprovacaoLiquida": 0
			},
			"fundamentos_sistemas_embarcados": {
				"nome": "Fundamentos de Sistemas Embarcados",
				"Matriculados": 48,
				"Aprovados": 23,
				"Reprovados": 21,
				"Trancados": 4,
				"Cancelados": 0,
				"MediaGeral": 4.58,
				"TaxadeAprovacao": 47.92,
				"TaxadeAprovacaoLiquida": 52.27,
				"MargemDeAprovacaoLiquida": 4.36
			},
			"grafos": {
				"nome": "Grafos e Algoritmos Computacionais",
				"Matriculados": 14,
				"Aprovados": 7,
				"Reprovados": 5,
				"Trancados": 1,
				"Cancelados": 1,
				"MediaGeral": 4.08,
				"TaxadeAprovacao": 53.85,
				"TaxadeAprovacaoLiquida": 58.33,
				"MargemDeAprovacaoLiquida": 4.49
			},
			"informatica_et_socie": {
				"nome": "Informatica, Etica e Sociedade",
				"Matriculados": 7,
				"Aprovados": 3,
				"Reprovados": 2,
				"Trancados": 2,
				"Cancelados": 0,
				"MediaGeral": 5.60,
				"TaxadeAprovacao": 42.86,
				"TaxadeAprovacaoLiquida": 60,
				"MargemDeAprovacaoLiquida": 17.14
			},
			"inteligencia_artificial": {
				"nome": "Inteligencia Artificial",
				"Matriculados": 15,
				"Aprovados": 10,
				"Reprovados": 3,
				"Trancados": 2,
				"Cancelados": 0,
				"MediaGeral": 6.17,
				"TaxadeAprovacao": 66.67,
				"TaxadeAprovacaoLiquida": 76.92,
				"MargemDeAprovacaoLiquida": 10.26
			},
			"interface_hardware_software": {
				"nome": "Interface Hardware Software",
				"Matriculados": 0,
				"Aprovados": 0,
				"Reprovados": 0,
				"Trancados": 0,
				"Cancelados": 0,
				"MediaGeral": 0,
				"TaxadeAprovacao": 0,
				"TaxadeAprovacaoLiquida": 0,
				"MargemDeAprovacaoLiquida": 0
			},
			"laboratorio_redes_computadores": {
				"nome": "Laboratorio de Redes de Computadores",
				"Matriculados": 22,
				"Aprovados": 17,
				"Reprovados": 4,
				"Trancados": 1,
				"Cancelados": 0,
				"MediaGeral": 6.60,
				"TaxadeAprovacao": 77.27,
				"TaxadeAprovacaoLiquida": 80.95,
				"MargemDeAprovacaoLiquida": 3.68
			},
			"LFC": {
				"nome": "Linguagens Formais e Computabilidade",
				"Matriculados": 24,
				"Aprovados": 15,
				"Reprovados": 8,
				"Trancados": 1,
				"Cancelados": 0,
				"MediaGeral": 4.83,
				"TaxadeAprovacao": 62.50,
				"TaxadeAprovacaoLiquida": 65.22,
				"MargemDeAprovacaoLiquida": 2.72
			},
			"logica_computacao": {
				"nome": "Logica de Computacao",
				"Matriculados": 49,
				"Aprovados": 37,
				"Reprovados": 9,
				"Trancados": 3,
				"Cancelados": 0,
				"MediaGeral": 6.08,
				"TaxadeAprovacao": 75.51,
				"TaxadeAprovacaoLiquida": 80.43,
				"MargemDeAprovacaoLiquida": 4.92
			},
			"metodos_tecnicas_pesquisa_compu": {
				"nome": "Metodos e Tecnicas de Pesquisa para Computacao",
				"Matriculados": 34,
				"Aprovados": 16,
				"Reprovados": 17,
				"Trancados": 1,
				"Cancelados": 0,
				"MediaGeral": 4.66,
				"TaxadeAprovacao": 47.06,
				"TaxadeAprovacaoLiquida": 48.48,
				"MargemDeAprovacaoLiquida": 1.43
			},
			"pratica_sistemas_digi": {
				"nome": "Praticas em Sistemas Digitais",
				"Matriculados": 16,
				"Aprovados": 7,
				"Reprovados": 7,
				"Trancados": 2,
				"Cancelados": 0,
				"MediaGeral": 4.13,
				"TaxadeAprovacao": 43.75,
				"TaxadeAprovacaoLiquida": 50,
				"MargemDeAprovacaoLiquida": 6.25
			},
			"pratica_orientada_em_comp_um": {
				"nome": "Pratica Orientada em Computacao I",
				"Matriculados": 5,
				"Aprovados": 4,
				"Reprovados": 1,
				"Trancados": 0,
				"Cancelados": 0,
				"MediaGeral": 6.54,
				"TaxadeAprovacao": 80,
				"TaxadeAprovacaoLiquida": 80,
				"MargemDeAprovacaoLiquida": 0
			},
			"pratica_orientada_em_comp_dois": {
				"nome": "Pratica Orientada em Computacao II",
				"Matriculados": 14,
				"Aprovados": 14,
				"Reprovados": 0,
				"Trancados": 0,
				"Cancelados": 0,
				"MediaGeral": 8.86,
				"TaxadeAprovacao": 100,
				"TaxadeAprovacaoLiquida": 100,
				"MargemDeAprovacaoLiquida": 0
			},
			"POO": {
				"nome": "Programacao Orientada a Objetos",
				"Matriculados": 16,
				"Aprovados": 5,
				"Reprovados": 6,
				"Trancados": 4,
				"Cancelados": 1,
				"MediaGeral": 3.74,
				"TaxadeAprovacao": 33.33,
				"TaxadeAprovacaoLiquida": 45.45,
				"MargemDeAprovacaoLiquida": 12.12
			},
			"programacao_paralela": {
				"nome": "Programacao Paralela",
				"Matriculados": 3,
				"Aprovados": 1,
				"Reprovados": 1,
				"Trancados": 1,
				"Cancelados": 0,
				"MediaGeral": 2.75,
				"TaxadeAprovacao": 33.33,
				"TaxadeAprovacaoLiquida": 50,
				"MargemDeAprovacaoLiquida": 16.67
			},
			"PAA": {
				"nome": "Projeto e Analise de Algoritmos",
				"Matriculados": 41,
				"Aprovados": 19,
				"Reprovados": 8,
				"Trancados": 14,
				"Cancelados": 0,
				"MediaGeral": 4.56,
				"TaxadeAprovacao": 46.34,
				"TaxadeAprovacaoLiquida": 70.37,
				"MargemDeAprovacaoLiquida": 24.03
			},
			"redes_computadores": {
				"nome": "Redes de Computadores",
				"Matriculados": 13,
				"Aprovados": 6,
				"Reprovados": 6,
				"Trancados": 1,
				"Cancelados": 0,
				"MediaGeral": 4.07,
				"TaxadeAprovacao": 46.15,
				"TaxadeAprovacaoLiquida": 50,
				"MargemDeAprovacaoLiquida": 3.85
			},
			"seminarios_comp": {
				"nome": "Seminarios em Computacao",
				"Matriculados": 0,
				"Aprovados": 0,
				"Reprovados": 0,
				"Trancados": 0,
				"Cancelados": 0,
				"MediaGeral": 0,
				"TaxadeAprovacao": 0,
				"TaxadeAprovacaoLiquida": 0,
				"MargemDeAprovacaoLiquida": 0
			},
			"sistemas_distribuidos": {
				"nome": "Sistemas Distribuidos",
				"Matriculados": 10,
				"Aprovados": 6,
				"Reprovados": 4,
				"Trancados": 0,
				"Cancelados": 0,
				"MediaGeral": 5.38,
				"TaxadeAprovacao": 60,
				"TaxadeAprovacaoLiquida": 60,
				"MargemDeAprovacaoLiquida": 0
			},
			"sistemas_operacionais": {
				"nome": "Sistemas Operacionais",
				"Matriculados": 8,
				"Aprovados": 8,
				"Reprovados": 0,
				"Trancados": 0,
				"Cancelados": 0,
				"MediaGeral": 7.71,
				"TaxadeAprovacao": 100,
				"TaxadeAprovacaoLiquida": 100,
				"MargemDeAprovacaoLiquida": 0
			},
			"trabalho_conclusao_curso_um": {
				"nome": "Trabalho de Conclusao de Curso I",
				"Matriculados": 7,
				"Aprovados": 5,
				"Reprovados": 2,
				"Trancados": 0,
				"Cancelados": 0,
				"MediaGeral": 5.79,
				"TaxadeAprovacao": 71.43,
				"TaxadeAprovacaoLiquida": 71.43,
				"MargemDeAprovacaoLiquida": 0
			},
			"trabalho_conclusao_curso_dois": {
				"nome": "Trabalho de Conclusao de Curso II",
				"Matriculados": 8,
				"Aprovados": 5,
				"Reprovados": 2,
				"Trancados": 1,
				"Cancelados": 0,
				"MediaGeral": 6.33,
				"TaxadeAprovacao": 62.50,
				"TaxadeAprovacaoLiquida": 71.43,
				"MargemDeAprovacaoLiquida": 8.93
			}
		},
		"2021.1": {
			"pi": {
				"nome": "Programacao Imperativa",
				"Matriculados": 7,
				"Aprovados": 3,
				"Reprovados": 1,
				"Trancados": 3,
				"Cancelados": 0,
				"MediaGeral": 5.18,
				"TaxadeAprovacao": 42.86,
				"TaxadeAprovacaoLiquida": 75,
				"MargemDeAprovacaoLiquida": 32.14
			},
			"pf": {
				"nome": "Programacao Funcional",
				"Matriculados": 69,
				"Aprovados": 14,
				"Reprovados": 43,
				"Trancados": 7,
				"Cancelados": 5,
				"MediaGeral": 2.68,
				"TaxadeAprovacao": 21.88,
				"TaxadeAprovacaoLiquida": 24.56,
				"MargemDeAprovacaoLiquida": 2.69
			},
			"arqui_computadores": {
				"nome": "Arquitetura de Computadores",
				"Matriculados": 7,
				"Aprovados": 0,
				"Reprovados": 4,
				"Trancados": 3,
				"Cancelados": 0,
				"MediaGeral": 0.73,
				"TaxadeAprovacao": 0,
				"TaxadeAprovacaoLiquida": 0,
				"MargemDeAprovacaoLiquida": 0
			},
			"banco_dados_um": {
				"nome": "Banco de Dados I",
				"Matriculados": 22,
				"Aprovados": 10,
				"Reprovados": 11,
				"Trancados": 1,
				"Cancelados": 0,
				"MediaGeral": 4.14,
				"TaxadeAprovacao": 45.45,
				"TaxadeAprovacaoLiquida": 47.62,
				"MargemDeAprovacaoLiquida": 2.16
			},
			"compiladores": {
				"nome": "Compiladores",
				"Matriculados": 8,
				"Aprovados": 2,
				"Reprovados": 6,
				"Trancados": 0,
				"Cancelados": 0,
				"MediaGeral": 2.84,
				"TaxadeAprovacao": 25,
				"TaxadeAprovacaoLiquida": 25,
				"MargemDeAprovacaoLiquida": 0
			},
			"eng_software_um": {
				"nome": "Engenharia de Software I",
				"Matriculados": 29,
				"Aprovados": 22,
				"Reprovados": 5,
				"Trancados": 1,
				"Cancelados": 1,
				"MediaGeral": 6.24,
				"TaxadeAprovacao": 78.57,
				"TaxadeAprovacaoLiquida": 81.48,
				"MargemDeAprovacaoLiquida": 2.91
			},
			"eng_software_dois": {
				"nome": "Engenharia de Software II",
				"Matriculados": 10,
				"Aprovados": 2,
				"Reprovados": 7,
				"Trancados": 1,
				"Cancelados": 0,
				"MediaGeral": 2.13,
				"TaxadeAprovacao": 20,
				"TaxadeAprovacaoLiquida": 22.22,
				"MargemDeAprovacaoLiquida": 2.22
			},

			"estagio_supervisionado_compu": {
				"nome": "Estagio Supervisionado em Computacao",
				"Matriculados": 6,
				"Aprovados": 5,
				"Reprovados": 0,
				"Trancados": 0,
				"Cancelados": 0,
				"MediaGeral": 9.60,
				"TaxadeAprovacao": 83.33,
				"TaxadeAprovacaoLiquida": 83.33,
				"MargemDeAprovacaoLiquida": 0
			},

			"ED": {
				"nome": "Estrutura de Dados",
				"Matriculados": 50,
				"Aprovados": 28,
				"Reprovados": 14,
				"Trancados": 8,
				"Cancelados": 0,
				"MediaGeral": 5.06,
				"TaxadeAprovacao": 56,
				"TaxadeAprovacaoLiquida": 66.67,
				"MargemDeAprovacaoLiquida": 10.67
			},
			"fundamentos_sistemas_digitais": {
				"nome": "Fundamentos de Sistemas Digitais",
				"Matriculados": 41,
				"Aprovados": 26,
				"Reprovados": 10,
				"Trancados": 5,
				"Cancelados": 0,
				"MediaGeral": 5.67,
				"TaxadeAprovacao": 63.41,
				"TaxadeAprovacaoLiquida": 72.22,
				"MargemDeAprovacaoLiquida": 8.81
			},
			"fundamentos_sistemas_embarcados": {
				"nome": "Fundamentos de Sistemas Embarcados",
				"Matriculados": 21,
				"Aprovados": 1,
				"Reprovados": 14,
				"Trancados": 0,
				"Cancelados": 6,
				"MediaGeral": 0.85,
				"TaxadeAprovacao": 4.76,
				"TaxadeAprovacaoLiquida": 6.67,
				"MargemDeAprovacaoLiquida": 1.90
			},
			"grafos": {
				"nome": "Grafos e Algoritmos Computacionais",
				"Matriculados": 24,
				"Aprovados": 21,
				"Reprovados": 2,
				"Trancados": 1,
				"Cancelados": 0,
				"MediaGeral": 7.17,
				"TaxadeAprovacao": 87.50,
				"TaxadeAprovacaoLiquida": 91.30,
				"MargemDeAprovacaoLiquida": 3.80
			},
			"informatica_et_socie": {
				"nome": "Informatica, Etica e Sociedade",
				"Matriculados": 53,
				"Aprovados": 44,
				"Reprovados": 2,
				"Trancados": 2,
				"Cancelados": 5,
				"MediaGeral": 8.68,
				"TaxadeAprovacao": 91.67,
				"TaxadeAprovacaoLiquida": 95.65,
				"MargemDeAprovacaoLiquida": 3.99
			},
			"inteligencia_artificial": {
				"nome": "Inteligencia Artificial",
				"Matriculados": 8,
				"Aprovados": 4,
				"Reprovados": 4,
				"Trancados": 0,
				"Cancelados": 0,
				"MediaGeral": 3.39,
				"TaxadeAprovacao": 50,
				"TaxadeAprovacaoLiquida": 50,
				"MargemDeAprovacaoLiquida": 0
			},
			"interface_hardware_software": {
				"nome": "Interface Hardware Software",
				"Matriculados": 24,
				"Aprovados": 7,
				"Reprovados": 15,
				"Trancados": 2,
				"Cancelados": 0,
				"MediaGeral": 2.08,
				"TaxadeAprovacao": 29.17,
				"TaxadeAprovacaoLiquida": 31.82,
				"MargemDeAprovacaoLiquida": 2.65
			},
			"laboratorio_redes_computadores": {
				"nome": "Laboratorio de Redes de Computadores",
				"Matriculados": 16,
				"Aprovados": 7,
				"Reprovados": 9,
				"Trancados": 0,
				"Cancelados": 0,
				"MediaGeral": 3.43,
				"TaxadeAprovacao": 43.75,
				"TaxadeAprovacaoLiquida": 43.75,
				"MargemDeAprovacaoLiquida": 0
			},
			"LFC": {
				"nome": "Linguagens Formais e Computabilidade",
				"Matriculados": 37,
				"Aprovados": 26,
				"Reprovados": 11,
				"Trancados": 0,
				"Cancelados": 0,
				"MediaGeral": 4.76,
				"TaxadeAprovacao": 70.27,
				"TaxadeAprovacaoLiquida": 70.27,
				"MargemDeAprovacaoLiquida": 0
			},
			"logica_computacao": {
				"nome": "Logica de Computacao",
				"Matriculados": 17,
				"Aprovados": 9,
				"Reprovados": 7,
				"Trancados": 1,
				"Cancelados": 0,
				"MediaGeral": 4.14,
				"TaxadeAprovacao": 52.94,
				"TaxadeAprovacaoLiquida": 56.25,
				"MargemDeAprovacaoLiquida": 3.31
			},
			"metodos_tecnicas_pesquisa_compu": {
				"nome": "Metodos e Tecnicas de Pesquisa para Computacao",
				"Matriculados": 41,
				"Aprovados": 29,
				"Reprovados": 10,
				"Trancados": 0,
				"Cancelados": 2,
				"MediaGeral": 6.06,
				"TaxadeAprovacao": 74.36,
				"TaxadeAprovacaoLiquida": 74.36,
				"MargemDeAprovacaoLiquida": 0
			},
			"pratica_sistemas_digi": {
				"nome": "Praticas em Sistemas Digitais",
				"Matriculados": 37,
				"Aprovados": 18,
				"Reprovados": 15,
				"Trancados": 4,
				"Cancelados": 0,
				"MediaGeral": 4.82,
				"TaxadeAprovacao": 48.65,
				"TaxadeAprovacaoLiquida": 54.55,
				"MargemDeAprovacaoLiquida": 5.90
			},
			"pratica_orientada_em_comp_um": {
				"nome": "Pratica Orientada em Computacao I",
				"Matriculados": 8,
				"Aprovados": 7,
				"Reprovados": 1,
				"Trancados": 0,
				"Cancelados": 0,
				"MediaGeral": 7.65,
				"TaxadeAprovacao": 87.50,
				"TaxadeAprovacaoLiquida": 87.50,
				"MargemDeAprovacaoLiquida": 0
			},
			"pratica_orientada_em_comp_dois": {
				"nome": "Pratica Orientada em Computacao II",
				"Matriculados": 3,
				"Aprovados": 3,
				"Reprovados": 0,
				"Trancados": 0,
				"Cancelados": 0,
				"MediaGeral": 8.10,
				"TaxadeAprovacao": 100,
				"TaxadeAprovacaoLiquida": 100,
				"MargemDeAprovacaoLiquida": 0
			},
			"POO": {
				"nome": "Programacao Orientada a Objetos",
				"Matriculados": 63,
				"Aprovados": 38,
				"Reprovados": 20,
				"Trancados": 5,
				"Cancelados": 0,
				"MediaGeral": 6.16,
				"TaxadeAprovacao": 60.32,
				"TaxadeAprovacaoLiquida": 65.52,
				"MargemDeAprovacaoLiquida": 5.20
			},
			"programacao_paralela": {
				"nome": "Programacao Paralela",
				"Matriculados": 21,
				"Aprovados": 17,
				"Reprovados": 4,
				"Trancados": 0,
				"Cancelados": 0,
				"MediaGeral": 6.03,
				"TaxadeAprovacao": 80.95,
				"TaxadeAprovacaoLiquida": 80.95,
				"MargemDeAprovacaoLiquida": 0
			},
			"PAA": {
				"nome": "Projeto e Analise de Algoritmos",
				"Matriculados": 12,
				"Aprovados": 2,
				"Reprovados": 8,
				"Trancados": 2,
				"Cancelados": 0,
				"MediaGeral": 1.73,
				"TaxadeAprovacao": 16.67,
				"TaxadeAprovacaoLiquida": 20,
				"MargemDeAprovacaoLiquida": 3.33
			},
			"redes_computadores": {
				"nome": "Redes de Computadores",
				"Matriculados": 28,
				"Aprovados": 20,
				"Reprovados": 5,
				"Trancados": 2,
				"Cancelados": 1,
				"MediaGeral": 5.53,
				"TaxadeAprovacao": 74.07,
				"TaxadeAprovacaoLiquida": 80,
				"MargemDeAprovacaoLiquida": 5.93
			},
			"seminarios_comp": {
				"nome": "Seminarios em Computacao",
				"Matriculados": 68,
				"Aprovados": 57,
				"Reprovados": 4,
				"Trancados": 2,
				"Cancelados": 5,
				"MediaGeral": 8.77,
				"TaxadeAprovacao": 90.48,
				"TaxadeAprovacaoLiquida": 93.44,
				"MargemDeAprovacaoLiquida": 2.97
			},
			"sistemas_distribuidos": {
				"nome": "Sistemas Distribuidos",
				"Matriculados": 0,
				"Aprovados": 0,
				"Reprovados": 0,
				"Trancados": 0,
				"Cancelados": 0,
				"MediaGeral": 0,
				"TaxadeAprovacao": 0,
				"TaxadeAprovacaoLiquida": 0,
				"MargemDeAprovacaoLiquida": 0
			},
			"sistemas_operacionais": {
				"nome": "Sistemas Operacionais",
				"Matriculados": 31,
				"Aprovados": 17,
				"Reprovados": 7,
				"Trancados": 7,
				"Cancelados": 0,
				"MediaGeral": 4.50,
				"TaxadeAprovacao": 54.84,
				"TaxadeAprovacaoLiquida": 70.83,
				"MargemDeAprovacaoLiquida": 15.99
			},
			"trabalho_conclusao_curso_um": {
				"nome": "Trabalho de Conclusao de Curso I",
				"Matriculados": 9,
				"Aprovados": 8,
				"Reprovados": 1,
				"Trancados": 0,
				"Cancelados": 0,
				"MediaGeral": 7.70,
				"TaxadeAprovacao": 88.89,
				"TaxadeAprovacaoLiquida": 88.89,
				"MargemDeAprovacaoLiquida": 0
			},
			"trabalho_conclusao_curso_dois": {
				"nome": "Trabalho de Conclusao de Curso II",
				"Matriculados": 11,
				"Aprovados": 6,
				"Reprovados": 5,
				"Trancados": 0,
				"Cancelados": 0,
				"MediaGeral": 5.35,
				"TaxadeAprovacao": 54.55,
				"TaxadeAprovacaoLiquida": 54.55,
				"MargemDeAprovacaoLiquida": 0
			}
		},
		"2021.2": {
			"pi": {
				"nome": "Programacao Imperativa",
				"Matriculados": 53,
				"Aprovados": 30,
				"Reprovados": 13,
				"Trancados": 9,
				"Cancelados": 1,
				"MediaGeral": 5.55,
				"TaxadeAprovacao": 57.69,
				"TaxadeAprovacaoLiquida": 69.77,
				"MargemDeAprovacaoLiquida": 12.08
			},
			"pf": {
				"nome": "Programacao Funcional",
				"Matriculados": 54,
				"Aprovados": 20,
				"Reprovados": 29,
				"Trancados": 4,
				"Cancelados": 1,
				"MediaGeral": 3.94,
				"TaxadeAprovacao": 37.74,
				"TaxadeAprovacaoLiquida": 40.82,
				"MargemDeAprovacaoLiquida": 3.08
			},
			"arqui_computadores": {
				"nome": "Arquitetura de Computadores",
				"Matriculados": 74,
				"Aprovados": 44,
				"Reprovados": 22,
				"Trancados": 8,
				"Cancelados": 0,
				"MediaGeral": 5.75,
				"TaxadeAprovacao": 59.46,
				"TaxadeAprovacaoLiquida": 66.67,
				"MargemDeAprovacaoLiquida": 7.21
			},
			"banco_dados_um": {
				"nome": "Banco de Dados I",
				"Matriculados": 24,
				"Aprovados": 14,
				"Reprovados": 8,
				"Trancados": 2,
				"Cancelados": 0,
				"MediaGeral": 4.55,
				"TaxadeAprovacao": 58.33,
				"TaxadeAprovacaoLiquida": 63.64,
				"MargemDeAprovacaoLiquida": 5.30
			},
			"compiladores": {
				"nome": "Compiladores",
				"Matriculados": 17,
				"Aprovados": 11,
				"Reprovados": 3,
				"Trancados": 1,
				"Cancelados": 2,
				"MediaGeral": 5.62,
				"TaxadeAprovacao": 73.33,
				"TaxadeAprovacaoLiquida": 78.57,
				"MargemDeAprovacaoLiquida": 5.24
			},
			"eng_software_um": {
				"nome": "Engenharia de Software I",
				"Matriculados": 18,
				"Aprovados": 18,
				"Reprovados": 0,
				"Trancados": 0,
				"Cancelados": 0,
				"MediaGeral": 9.94,
				"TaxadeAprovacao": 100,
				"TaxadeAprovacaoLiquida": 100,
				"MargemDeAprovacaoLiquida": 0
			},
			"eng_software_dois": {
				"nome": "Engenharia de Software II",
				"Matriculados": 43,
				"Aprovados": 27,
				"Reprovados": 11,
				"Trancados": 5,
				"Cancelados": 0,
				"MediaGeral": 5.65,
				"TaxadeAprovacao": 62.79,
				"TaxadeAprovacaoLiquida": 71.05,
				"MargemDeAprovacaoLiquida": 8.26
			},

			"estagio_supervisionado_compu": {
				"nome": "Estagio Supervisionado em Computacao",
				"Matriculados": 7,
				"Aprovados": 6,
				"Reprovados": 0,
				"Trancados": 0,
				"Cancelados": 1,
				"MediaGeral": 10,
				"TaxadeAprovacao": 100,
				"TaxadeAprovacaoLiquida": 100,
				"MargemDeAprovacaoLiquida": 0
			},

			"ED": {
				"nome": "Estrutura de Dados",
				"Matriculados": 27,
				"Aprovados": 6,
				"Reprovados": 16,
				"Trancados": 5,
				"Cancelados": 0,
				"MediaGeral": 2.29,
				"TaxadeAprovacao": 22.22,
				"TaxadeAprovacaoLiquida": 27.27,
				"MargemDeAprovacaoLiquida": 5.05
			},
			"fundamentos_sistemas_digitais": {
				"nome": "Fundamentos de Sistemas Digitais",
				"Matriculados": 0,
				"Aprovados": 0,
				"Reprovados": 0,
				"Trancados": 0,
				"Cancelados": 0,
				"MediaGeral": 0,
				"TaxadeAprovacao": 0,
				"TaxadeAprovacaoLiquida": 0,
				"MargemDeAprovacaoLiquida": 0
			},
			"fundamentos_sistemas_embarcados": {
				"nome": "Fundamentos de Sistemas Embarcados",
				"Matriculados": 70,
				"Aprovados": 8,
				"Reprovados": 43,
				"Trancados": 19,
				"Cancelados": 0,
				"MediaGeral": 1.39,
				"TaxadeAprovacao": 11.43,
				"TaxadeAprovacaoLiquida": 15.69,
				"MargemDeAprovacaoLiquida": 4.26
			},
			"grafos": {
				"nome": "Grafos e Algoritmos Computacionais",
				"Matriculados": 17,
				"Aprovados": 1,
				"Reprovados": 13,
				"Trancados": 3,
				"Cancelados": 0,
				"MediaGeral": 1.60,
				"TaxadeAprovacao": 5.88,
				"TaxadeAprovacaoLiquida": 7.14,
				"MargemDeAprovacaoLiquida": 1.26
			},
			"informatica_et_socie": {
				"nome": "Informatica, Etica e Sociedade",
				"Matriculados": 33,
				"Aprovados": 15,
				"Reprovados": 10,
				"Trancados": 7,
				"Cancelados": 1,
				"MediaGeral": 5.30,
				"TaxadeAprovacao": 46.88,
				"TaxadeAprovacaoLiquida": 60,
				"MargemDeAprovacaoLiquida": 13.13
			},
			"inteligencia_artificial": {
				"nome": "Inteligencia Artificial",
				"Matriculados": 31,
				"Aprovados": 19,
				"Reprovados": 8,
				"Trancados": 4,
				"Cancelados": 0,
				"MediaGeral": 6.06,
				"TaxadeAprovacao": 61.29,
				"TaxadeAprovacaoLiquida": 70.37,
				"MargemDeAprovacaoLiquida": 9.08
			},
			"interface_hardware_software": {
				"nome": "Interface Hardware Software",
				"Matriculados": 0,
				"Aprovados": 0,
				"Reprovados": 0,
				"Trancados": 0,
				"Cancelados": 0,
				"MediaGeral": 0,
				"TaxadeAprovacao": 0,
				"TaxadeAprovacaoLiquida": 0,
				"MargemDeAprovacaoLiquida": 0
			},
			"laboratorio_redes_computadores": {
				"nome": "Laboratorio de Redes de Computadores",
				"Matriculados": 26,
				"Aprovados": 17,
				"Reprovados": 6,
				"Trancados": 2,
				"Cancelados": 1,
				"MediaGeral": 5.52,
				"TaxadeAprovacao": 68,
				"TaxadeAprovacaoLiquida": 73.91,
				"MargemDeAprovacaoLiquida": 5.91
			},
			"LFC": {
				"nome": "Linguagens Formais e Computabilidade",
				"Matriculados": 26,
				"Aprovados": 2,
				"Reprovados": 12,
				"Trancados": 12,
				"Cancelados": 0,
				"MediaGeral": 2.01,
				"TaxadeAprovacao": 7.69,
				"TaxadeAprovacaoLiquida": 14.29,
				"MargemDeAprovacaoLiquida": 6.59
			},
			"logica_computacao": {
				"nome": "Logica de Computacao",
				"Matriculados": 47,
				"Aprovados": 37,
				"Reprovados": 7,
				"Trancados": 3,
				"Cancelados": 0,
				"MediaGeral": 6.23,
				"TaxadeAprovacao": 78.72,
				"TaxadeAprovacaoLiquida": 84.09,
				"MargemDeAprovacaoLiquida": 5.37
			},
			"metodos_tecnicas_pesquisa_compu": {
				"nome": "Metodos e Tecnicas de Pesquisa para Computacao",
				"Matriculados": 35,
				"Aprovados": 22,
				"Reprovados": 9,
				"Trancados": 4,
				"Cancelados": 0,
				"MediaGeral": 5.07,
				"TaxadeAprovacao": 62.86,
				"TaxadeAprovacaoLiquida": 70.97,
				"MargemDeAprovacaoLiquida": 8.11
			},
			"pratica_sistemas_digi": {
				"nome": "Praticas em Sistemas Digitais",
				"Matriculados": 0,
				"Aprovados": 0,
				"Reprovados": 0,
				"Trancados": 0,
				"Cancelados": 0,
				"MediaGeral": 0,
				"TaxadeAprovacao": 0,
				"TaxadeAprovacaoLiquida": 0,
				"MargemDeAprovacaoLiquida": 0
			},
			"pratica_orientada_em_comp_um": {
				"nome": "Pratica Orientada em Computacao I",
				"Matriculados": 6,
				"Aprovados": 5,
				"Reprovados": 0,
				"Trancados": 1,
				"Cancelados": 0,
				"MediaGeral": 7.70,
				"TaxadeAprovacao": 83.33,
				"TaxadeAprovacaoLiquida": 100,
				"MargemDeAprovacaoLiquida": 16.67
			},
			"pratica_orientada_em_comp_dois": {
				"nome": "Pratica Orientada em Computacao II",
				"Matriculados": 8,
				"Aprovados": 8,
				"Reprovados": 0,
				"Trancados": 0,
				"Cancelados": 0,
				"MediaGeral": 8.50,
				"TaxadeAprovacao": 100,
				"TaxadeAprovacaoLiquida": 100,
				"MargemDeAprovacaoLiquida": 0
			},
			"POO": {
				"nome": "Programacao Orientada a Objetos",
				"Matriculados": 15,
				"Aprovados": 6,
				"Reprovados": 8,
				"Trancados": 1,
				"Cancelados": 0,
				"MediaGeral": 3.19,
				"TaxadeAprovacao": 40,
				"TaxadeAprovacaoLiquida": 42.86,
				"MargemDeAprovacaoLiquida": 2.86
			},
			"programacao_paralela": {
				"nome": "Programacao Paralela",
				"Matriculados": 8,
				"Aprovados": 7,
				"Reprovados": 1,
				"Trancados": 0,
				"Cancelados": 0,
				"MediaGeral": 5.84,
				"TaxadeAprovacao": 87.50,
				"TaxadeAprovacaoLiquida": 87.50,
				"MargemDeAprovacaoLiquida": 0
			},
			"PAA": {
				"nome": "Projeto e Analise de Algoritmos",
				"Matriculados": 62,
				"Aprovados": 9,
				"Reprovados": 33,
				"Trancados": 19,
				"Cancelados": 1,
				"MediaGeral": 2.08,
				"TaxadeAprovacao": 14.75,
				"TaxadeAprovacaoLiquida": 21.43,
				"MargemDeAprovacaoLiquida": 6.67
			},
			"redes_computadores": {
				"nome": "Redes de Computadores",
				"Matriculados": 6,
				"Aprovados": 4,
				"Reprovados": 2,
				"Trancados": 0,
				"Cancelados": 0,
				"MediaGeral": 5.25,
				"TaxadeAprovacao": 66.67,
				"TaxadeAprovacaoLiquida": 66.67,
				"MargemDeAprovacaoLiquida": 0
			},
			"seminarios_comp": {
				"nome": "Seminarios em Computacao",
				"Matriculados": 0,
				"Aprovados": 0,
				"Reprovados": 0,
				"Trancados": 0,
				"Cancelados": 0,
				"MediaGeral": 0,
				"TaxadeAprovacao": 0,
				"TaxadeAprovacaoLiquida": 0,
				"MargemDeAprovacaoLiquida": 0
			},
			"sistemas_distribuidos": {
				"nome": "Sistemas Distribuidos",
				"Matriculados": 26,
				"Aprovados": 19,
				"Reprovados": 3,
				"Trancados": 2,
				"Cancelados": 2,
				"MediaGeral": 6.87,
				"TaxadeAprovacao": 79.17,
				"TaxadeAprovacaoLiquida": 86.36,
				"MargemDeAprovacaoLiquida": 7.20
			},
			"sistemas_operacionais": {
				"nome": "Sistemas Operacionais",
				"Matriculados": 15,
				"Aprovados": 7,
				"Reprovados": 6,
				"Trancados": 2,
				"Cancelados": 0,
				"MediaGeral": 3.98,
				"TaxadeAprovacao": 46.67,
				"TaxadeAprovacaoLiquida": 53.85,
				"MargemDeAprovacaoLiquida": 7.18
			},
			"trabalho_conclusao_curso_um": {
				"nome": "Trabalho de Conclusao de Curso I",
				"Matriculados": 7,
				"Aprovados": 5,
				"Reprovados": 2,
				"Trancados": 0,
				"Cancelados": 0,
				"MediaGeral": 6.96,
				"TaxadeAprovacao": 71.43,
				"TaxadeAprovacaoLiquida": 71.43,
				"MargemDeAprovacaoLiquida": 0
			},
			"trabalho_conclusao_curso_dois": {
				"nome": "Trabalho de Conclusao de Curso II",
				"Matriculados": 12,
				"Aprovados": 9,
				"Reprovados": 3,
				"Trancados": 0,
				"Cancelados": 0,
				"MediaGeral": 7.18,
				"TaxadeAprovacao": 75,
				"TaxadeAprovacaoLiquida": 75,
				"MargemDeAprovacaoLiquida": 0
			}
		}
	}
}
